cpilatam/__init__.py
cpilatam/data/colombia.csv
cpilatam/data/peru.csv
cpilatam/exc.py
cpilatam/logger.py
cpilatam/names.py
cpilatam/parsers/__init__.py
cpilatam/parsers/base.py
cpilatam/parsers/chile.py
cpilatam/parsers/colombia.py
cpilatam/parsers/peru.py
cpilatam/schemas.py
cpilatam/settings.py
cpilatam-2023.11.1.dist-info/METADATA
cpilatam-2023.11.1.dist-info/WHEEL
cpilatam-2023.11.1.dist-info/RECORD
